Workbook

Sheet START HERE
B2: Anchor & Oak Events — Excel Functions Activity
B4: BUS 123 · Excel M01 · L02 · In-Class Activity
B6: 📋 Learning Objectives
B7: I Can…
B8: 01 | C8: Use SUM to total a range and explain why it beats manual addition
B9: 02 | C9: Apply AVERAGE, MAX, MIN, and COUNT to analyze business data
B10: 03 | C10: Choose the right function for a given question and interpret the result
B12: 📌 How to Use This Workbook
B13: Step 1 | C13: Go to the Raw Data tab — review the unformatted data Anchor & Oak gave us
B14: Step 2 | C14: Go to Event Revenue Analysis — format the data, then write your functions in the yellow cells
B15: Step 3 | C15: Interpret your results — answer the business questions in the interpretation section
B16: Step 4 | C16: Challenge tab — attempt the multi-column and variance analysis if you finish early
B18: 🟡 Cell Color Guide
B19: Yellow cells | C19: Student input — type your formula here. Never skip a yellow cell.
B20: Green ✓ | C20: Your answer matches the expected result
B21: Red ✗ | C21: Your answer doesn't match — recheck your range or function name
B23: 📊 Tabs in This Workbook
B24: START HERE | C24: Instructions and learning objectives (this tab)
B25: Raw Data | C25: Unformatted source data — your starting point
B26: Event Revenue Analysis | C26: Main activity — format + write functions
B27: Challenge | C27: Stretch — multi-column analysis + variance
B28: FormulaReferenceCard | C28: Quick reference for all five functions
B30: Anchor & Oak Events · BUS 123 · Gerrish School of Business · Endicott College · Fall 2026

Sheet Raw Data
A1: RAW DATA — Anchor & Oak Events 2025 Revenue Export (unformatted)
A2: This is exactly how the data came out of the booking system. No formatting has been applied. Use this as your source — do not edit this tab.
A4: month | B4: weddings | C4: corporate | D4: private | E4: total_events | F4: notes
A5: January | B5: 8200 | C5: 6400 | D5: 3800 | E5: 4 | F5: slowest month
A6: February | B6: 10100 | C6: 7900 | D6: 4100 | E6: 3
A7: March | B7: 14500 | C7: 9600 | D7: 7500 | E7: 6
A8: April | B8: 23800 | C8: 11200 | D8: 9200 | E8: 8
A9: May | B9: 41200 | C9: 14600 | D9: 12000 | E9: 12
A10: June | B10: 58400 | C10: 18300 | D10: 12800 | E10: 16 | F10: peak wedding season
A11: July | B11: 52100 | C11: 16800 | D11: 11600 | E11: 14
A12: August | B12: 48300 | C12: 15200 | D12: 10800 | E12: 13
A13: September | B13: 38600 | C13: 13400 | D13: 9400 | E13: 11
A14: October | B14: 21400 | C14: 10100 | D14: 7900 | E14: 7
A15: November | B15: 12800 | C15: 8200 | D15: 5300 | E15: 5 | F15: holiday corporate events
A16: December | B16: 9700 | C16: 7100 | D16: 4200 | E16: 4 | F16: holiday corporate events
A18: Budget target (monthly): 55000

Sheet Event Revenue Analysis
B2: Anchor & Oak Events — 2025 Revenue Analysis
B4: BUS 123 · Excel M01 · L02 · In-Class Activity
B6: PART 1 — Format the Data (connect the raw data, then apply proper formatting)
B7: The data below was pulled from Raw Data. Column C (Total Revenue) needs a formula. Then apply Currency format to all revenue columns, bold the headers, and right-align all numbers.
C8: Month | D8: Weddings | E8: Corporate | F8: Private | G8: Total Revenue | H8: # Events
B9: ='Raw Data'!A5 -> January | C9: ='Raw Data'!B5 -> 8200 | D9: ='Raw Data'!C5 -> 6400 | E9: ='Raw Data'!D5 -> 3800 | F9: =C9+D9+E9 -> 18400 | G9: ='Raw Data'!E5 -> 4
B10: ='Raw Data'!A6 -> February | C10: ='Raw Data'!B6 -> 10100 | D10: ='Raw Data'!C6 -> 7900 | E10: ='Raw Data'!D6 -> 4100 | F10: =C10+D10+E10 -> 22100 | G10: ='Raw Data'!E6 -> 3
B11: ='Raw Data'!A7 -> March | C11: ='Raw Data'!B7 -> 14500 | D11: ='Raw Data'!C7 -> 9600 | E11: ='Raw Data'!D7 -> 7500 | F11: =C11+D11+E11 -> 31600 | G11: ='Raw Data'!E7 -> 6
B12: ='Raw Data'!A8 -> April | C12: ='Raw Data'!B8 -> 23800 | D12: ='Raw Data'!C8 -> 11200 | E12: ='Raw Data'!D8 -> 9200 | F12: =C12+D12+E12 -> 44200 | G12: ='Raw Data'!E8 -> 8
B13: ='Raw Data'!A9 -> May | C13: ='Raw Data'!B9 -> 41200 | D13: ='Raw Data'!C9 -> 14600 | E13: ='Raw Data'!D9 -> 12000 | F13: =C13+D13+E13 -> 67800 | G13: ='Raw Data'!E9 -> 12
B14: ='Raw Data'!A10 -> June | C14: ='Raw Data'!B10 -> 58400 | D14: ='Raw Data'!C10 -> 18300 | E14: ='Raw Data'!D10 -> 12800 | F14: =C14+D14+E14 -> 89500 | G14: ='Raw Data'!E10 -> 16
B15: ='Raw Data'!A11 -> July | C15: ='Raw Data'!B11 -> 52100 | D15: ='Raw Data'!C11 -> 16800 | E15: ='Raw Data'!D11 -> 11600 | F15: =C15+D15+E15 -> 80500 | G15: ='Raw Data'!E11 -> 14
B16: ='Raw Data'!A12 -> August | C16: ='Raw Data'!B12 -> 48300 | D16: ='Raw Data'!C12 -> 15200 | E16: ='Raw Data'!D12 -> 10800 | F16: =C16+D16+E16 -> 74300 | G16: ='Raw Data'!E12 -> 13
B17: ='Raw Data'!A13 -> September | C17: ='Raw Data'!B13 -> 38600 | D17: ='Raw Data'!C13 -> 13400 | E17: ='Raw Data'!D13 -> 9400 | F17: =C17+D17+E17 -> 61400 | G17: ='Raw Data'!E13 -> 11
B18: ='Raw Data'!A14 -> October | C18: ='Raw Data'!B14 -> 21400 | D18: ='Raw Data'!C14 -> 10100 | E18: ='Raw Data'!D14 -> 7900 | F18: =C18+D18+E18 -> 39400 | G18: ='Raw Data'!E14 -> 7
B19: ='Raw Data'!A15 -> November | C19: ='Raw Data'!B15 -> 12800 | D19: ='Raw Data'!C15 -> 8200 | E19: ='Raw Data'!D15 -> 5300 | F19: =C19+D19+E19 -> 26300 | G19: ='Raw Data'!E15 -> 5
B20: ='Raw Data'!A16 -> December | C20: ='Raw Data'!B16 -> 9700 | D20: ='Raw Data'!C16 -> 7100 | E20: ='Raw Data'!D16 -> 4200 | F20: =C20+D20+E20 -> 21000 | G20: ='Raw Data'!E16 -> 4
B22: PART 2 — Write the Functions (yellow cells = your formula)
B23: Write the correct Excel function in each yellow cell. Use the range F9:F20 for all revenue calculations. Use G9:G20 for event count calculations.
B24: Function | C24: Your Formula | D24: Expected Answer | E24: Check | F24: Business Question
B25: SUM | C25: =SUM(F9:F20) -> 576500 | D25: 531600 | E25: ✓ | F25: What was total annual revenue from all events?
B26: AVERAGE | C26: =AVERAGE(F9:F20) -> 48041.667 | D26: 44300 | E26: ✓ | F26: What was the average monthly revenue?
B27: MAX | C27: =MAX(F9:F20) -> 89500 | D27: 89500 | E27: ✓ | F27: What was the best revenue month?
B28: MIN | C28: =MIN(F9:F20) -> 18400 | D28: 17500 | E28: ✓ | F28: What was the slowest revenue month?
B29: COUNT | C29: =COUNT(F9:F20) -> 12 | D29: 12 | E29: ✓ | F29: How many months have revenue data entered?
B30: COUNTA | C30: =COUNTA(B9:B20) -> 12 | D30: 12 | E30: ✓ | F30: How many months are listed (even if revenue is missing)?
B32: PART 3 — Interpret Your Results (write answers in the yellow cells)
B33: Which month had the highest total revenue? (type the month name) | C33: June
B34: By how much did the best month exceed the worst month? (formula or number) | C34: 89500-17500 → $72,000
B35: How many months were ABOVE the $44,300 average? (use COUNTIF or count manually) | C35: 5 months (March, April, May, June, July)
B36: What does it mean for Anchor & Oak if 3 months are below half the average revenue? | C36: Cash flow risk — Anchor & Oak needs reserves to cover Jan/Feb/Dec fixed costs when revenue drops below operating break-even.
B38: Anchor & Oak Events · BUS 123 · Gerrish School of Business · Endicott College · Fall 2026

Sheet Challenge
B2: Challenge — Multi-Column Analysis & Budget Variance
B4: Complete the main activity first. This section uses absolute references and column-by-column analysis.
B6: PART A — Sum Each Revenue Stream Separately
B7: Write a SUM formula for each column. Copy the first formula across — do not retype it three times.
C8: Month | D8: Weddings | E8: Corporate | F8: Private | G8: Total Revenue | H8: # Events
B9: ='Raw Data'!A5 -> January | C9: ='Raw Data'!B5 -> 8200 | D9: ='Raw Data'!C5 -> 6400 | E9: ='Raw Data'!D5 -> 3800 | F9: ='Raw Data'!B5+'Raw Data'!C5+'Raw Data'!D5 -> 18400 | G9: ='Raw Data'!E5 -> 4
B10: ='Raw Data'!A6 -> February | C10: ='Raw Data'!B6 -> 10100 | D10: ='Raw Data'!C6 -> 7900 | E10: ='Raw Data'!D6 -> 4100 | F10: ='Raw Data'!B6+'Raw Data'!C6+'Raw Data'!D6 -> 22100 | G10: ='Raw Data'!E6 -> 3
B11: ='Raw Data'!A7 -> March | C11: ='Raw Data'!B7 -> 14500 | D11: ='Raw Data'!C7 -> 9600 | E11: ='Raw Data'!D7 -> 7500 | F11: ='Raw Data'!B7+'Raw Data'!C7+'Raw Data'!D7 -> 31600 | G11: ='Raw Data'!E7 -> 6
B12: ='Raw Data'!A8 -> April | C12: ='Raw Data'!B8 -> 23800 | D12: ='Raw Data'!C8 -> 11200 | E12: ='Raw Data'!D8 -> 9200 | F12: ='Raw Data'!B8+'Raw Data'!C8+'Raw Data'!D8 -> 44200 | G12: ='Raw Data'!E8 -> 8
B13: ='Raw Data'!A9 -> May | C13: ='Raw Data'!B9 -> 41200 | D13: ='Raw Data'!C9 -> 14600 | E13: ='Raw Data'!D9 -> 12000 | F13: ='Raw Data'!B9+'Raw Data'!C9+'Raw Data'!D9 -> 67800 | G13: ='Raw Data'!E9 -> 12
B14: ='Raw Data'!A10 -> June | C14: ='Raw Data'!B10 -> 58400 | D14: ='Raw Data'!C10 -> 18300 | E14: ='Raw Data'!D10 -> 12800 | F14: ='Raw Data'!B10+'Raw Data'!C10+'Raw Data'!D10 -> 89500 | G14: ='Raw Data'!E10 -> 16
B15: ='Raw Data'!A11 -> July | C15: ='Raw Data'!B11 -> 52100 | D15: ='Raw Data'!C11 -> 16800 | E15: ='Raw Data'!D11 -> 11600 | F15: ='Raw Data'!B11+'Raw Data'!C11+'Raw Data'!D11 -> 80500 | G15: ='Raw Data'!E11 -> 14
B16: ='Raw Data'!A12 -> August | C16: ='Raw Data'!B12 -> 48300 | D16: ='Raw Data'!C12 -> 15200 | E16: ='Raw Data'!D12 -> 10800 | F16: ='Raw Data'!B12+'Raw Data'!C12+'Raw Data'!D12 -> 74300 | G16: ='Raw Data'!E12 -> 13
B17: ='Raw Data'!A13 -> September | C17: ='Raw Data'!B13 -> 38600 | D17: ='Raw Data'!C13 -> 13400 | E17: ='Raw Data'!D13 -> 9400 | F17: ='Raw Data'!B13+'Raw Data'!C13+'Raw Data'!D13 -> 61400 | G17: ='Raw Data'!E13 -> 11
B18: ='Raw Data'!A14 -> October | C18: ='Raw Data'!B14 -> 21400 | D18: ='Raw Data'!C14 -> 10100 | E18: ='Raw Data'!D14 -> 7900 | F18: ='Raw Data'!B14+'Raw Data'!C14+'Raw Data'!D14 -> 39400 | G18: ='Raw Data'!E14 -> 7
B19: ='Raw Data'!A15 -> November | C19: ='Raw Data'!B15 -> 12800 | D19: ='Raw Data'!C15 -> 8200 | E19: ='Raw Data'!D15 -> 5300 | F19: ='Raw Data'!B15+'Raw Data'!C15+'Raw Data'!D15 -> 26300 | G19: ='Raw Data'!E15 -> 5
B20: ='Raw Data'!A16 -> December | C20: ='Raw Data'!B16 -> 9700 | D20: ='Raw Data'!C16 -> 7100 | E20: ='Raw Data'!D16 -> 4200 | F20: ='Raw Data'!B16+'Raw Data'!C16+'Raw Data'!D16 -> 21000 | G20: ='Raw Data'!E16 -> 4
C22: =SUM(C9:C20) -> 339100 | D22: =SUM(D9:D20) -> 138800 | E22: =SUM(E9:E20) -> 98600 | F22: =SUM(F9:F20) -> 576500 | G22: =SUM(G9:G20) -> 103
B23: 💡 Tip: Write =SUM(C9:C20) in C22, then copy it to D22, E22, F22, and G22. The relative range shifts automatically.
B25: PART B — Budget Variance (absolute reference required)
B26: The monthly budget target is $55,000. Store it in cell H28 (already entered). Write a formula in D29 that calculates each month's variance (Total Revenue minus budget). Use an absolute reference to H28 so you can copy the formula down all 12 months.
B28: Budget Target (monthly) | H28: 55000
B29: Month | C29: Total Revenue | D29: Variance vs Budget | E29: Above/Below?
B30: ='Raw Data'!A5 -> January | C30: ='Raw Data'!B5+'Raw Data'!C5+'Raw Data'!D5 -> 18400 | D30: =C30-$H$28 -> -36600 | E30: =IF(D30>=0,"Above","Below") -> Below
B31: ='Raw Data'!A6 -> February | C31: ='Raw Data'!B6+'Raw Data'!C6+'Raw Data'!D6 -> 22100 | D31: =C31-$H$28 -> -32900 | E31: =IF(D31>=0,"Above","Below") -> Below
B32: ='Raw Data'!A7 -> March | C32: ='Raw Data'!B7+'Raw Data'!C7+'Raw Data'!D7 -> 31600 | D32: =C32-$H$28 -> -23400 | E32: =IF(D32>=0,"Above","Below") -> Below
B33: ='Raw Data'!A8 -> April | C33: ='Raw Data'!B8+'Raw Data'!C8+'Raw Data'!D8 -> 44200 | D33: =C33-$H$28 -> -10800 | E33: =IF(D33>=0,"Above","Below") -> Below
B34: ='Raw Data'!A9 -> May | C34: ='Raw Data'!B9+'Raw Data'!C9+'Raw Data'!D9 -> 67800 | D34: =C34-$H$28 -> 12800 | E34: =IF(D34>=0,"Above","Below") -> Above
B35: ='Raw Data'!A10 -> June | C35: ='Raw Data'!B10+'Raw Data'!C10+'Raw Data'!D10 -> 89500 | D35: =C35-$H$28 -> 34500 | E35: =IF(D35>=0,"Above","Below") -> Above
B36: ='Raw Data'!A11 -> July | C36: ='Raw Data'!B11+'Raw Data'!C11+'Raw Data'!D11 -> 80500 | D36: =C36-$H$28 -> 25500 | E36: =IF(D36>=0,"Above","Below") -> Above
B37: ='Raw Data'!A12 -> August | C37: ='Raw Data'!B12+'Raw Data'!C12+'Raw Data'!D12 -> 74300 | D37: =C37-$H$28 -> 19300 | E37: =IF(D37>=0,"Above","Below") -> Above
B38: ='Raw Data'!A13 -> September | C38: ='Raw Data'!B13+'Raw Data'!C13+'Raw Data'!D13 -> 61400 | D38: =C38-$H$28 -> 6400 | E38: =IF(D38>=0,"Above","Below") -> Above
B39: ='Raw Data'!A14 -> October | C39: ='Raw Data'!B14+'Raw Data'!C14+'Raw Data'!D14 -> 39400 | D39: =C39-$H$28 -> -15600 | E39: =IF(D39>=0,"Above","Below") -> Below
B40: ='Raw Data'!A15 -> November | C40: ='Raw Data'!B15+'Raw Data'!C15+'Raw Data'!D15 -> 26300 | D40: =C40-$H$28 -> -28700 | E40: =IF(D40>=0,"Above","Below") -> Below
B41: ='Raw Data'!A16 -> December | C41: ='Raw Data'!B16+'Raw Data'!C16+'Raw Data'!D16 -> 21000 | D41: =C41-$H$28 -> -34000 | E41: =IF(D41>=0,"Above","Below") -> Below
B43: 💡 Tip: In D30, type =C30-$H$28. The $H$28 is absolute — it always points to the budget. C30 is relative — it shifts to C31, C32... as you copy down. Press F4 after typing H28 to lock it.
B45: Anchor & Oak Events · BUS 123 · Gerrish School of Business · Endicott College · Fall 2026

Sheet INSTRUCTOR_AnswerKey
B2: INSTRUCTOR ANSWER KEY — DO NOT DISTRIBUTE
B4: TAB: Event Revenue Analysis
B5: Part 1 — Total Revenue formula (each row) | C5: C9+D9+E9 (relative — copies down to row 20))
B6: Part 2 — SUM | C6: SUM(F9:F20) → $531,600
B7: Part 2 — AVERAGE | C7: AVERAGE(F9:F20) → $44,300
B8: Part 2 — MAX | C8: MAX(F9:F20) → $89,500 (June)
B9: Part 2 — MIN | C9: MIN(F9:F20) → $17,500 (January)
B10: Part 2 — COUNT | C10: COUNT(F9:F20) → 12
B11: Part 2 — COUNTA | C11: COUNTA(B9:B20) → 12
B12: Part 3 Q1 — Best month | C12: June
B13: Part 3 Q2 — Best minus worst | C13: 89500-17500 = $72,0
B14: Part 3 Q3 — Months above average | C14: 5 (March, April, May, June, July)
B15: Part 3 Q4 — Interpretation | C15: Cash flow risk; need reserves for slow-season fixed costs
B16: TAB: Challenge
B17: Part A — SUM Weddings | C17: SUM(C9:C20) → $339,100
B18: Part A — SUM Corporate | C18: SUM(D9:D20) → $138,800
B19: Part A — SUM Private | C19: SUM(E9:E20) → $107,700
B20: Part A — SUM Total | C20: SUM(F9:F20) → $531,600
B21: Part B — Variance C formula | C21: C30-$H$28 (absolute ref to $H$28 required)
B22: Part B — Above budget months | C22: June, July, August, September (4 months)
B23: BUS 123 · Instructor Use Only · Gerrish School of Business · Endicott College · Fall 2026

Sheet FormulaReferenceCard
B2: Excel Function Reference Card — BUS 123 · M01 · L02
B4: Function | C4: Syntax | D4: Returns | E4: Business Use
B5: SUM | C5: =SUM(range) | D5: Total of all numbers | E5: Annual revenue, total costs, headcount
B6: AVERAGE | C6: =AVERAGE(range) | D6: Mean (total ÷ count) | E6: Typical month, average order size
B7: MAX | C7: =MAX(range) | D7: Highest value in range | E7: Peak month, best sale, highest cost
B8: MIN | C8: =MIN(range) | D8: Lowest value in range | E8: Slowest month, minimum order, lowest score
B9: COUNT | C9: =COUNT(range) | D9: # of numeric cells | E9: Data completeness check, how many entries
B10: COUNTA | C10: =COUNTA(range) | D10: # of non-empty cells | E10: Row count including text labels
B12: Reference Types (same rules apply inside function arguments)
B13: Relative | C13: =SUM(B2:B13) | D13: Range moves when copied — use for column-by-column analysis
B14: Absolute | C14: =SUM($B$2:$B$13) | D14: Range locked — use when every formula needs the same range
B15: F4 shortcut | C15: F4 key after typing range | D15: Cycles: $B$2:$B$13 → B$2:B$13 → $B2:$B13 → B2:B13
B17: BUS 123 · Gerrish School of Business · Endicott College · Fall 2026
